[ {
    "name": "Reisinformatie",
    "headers": [
        {
            "name": "Plan je reis",
            "topics": [
                {
                    "name": "Op dit moment",
                    "links": [
                            "Geen storingen",
                            "6 werkzaamheden"
                    ]
                },
                {
                    "name": "Voorzieningen",
                    "links": [
                        "Informatie per station",
                        "Bagage",
                        "Reizen met een functiebeperking",
                        "Alles over voorzieningen"
                    ]
                }
            ]
        },
        {
            "name": "Onderweg",
            "topics": [
                {
                    "name": "OV-Chipkaart",
                    "links": [
                        "In- en uitchecken",
                        "Saldo laden",
                        "Samenreiskorting",
                        "Fiets in de trein",
                        "Alles over de OV-Chipkaart"
                    ]
                },
                {
                    "name": "Bijzondere trajecten",
                    "links": [
                        "Intercity direct",
                        "Nachttreinen",
                        "R-net",
                        "Alle bijzondere trajecten"
                        
                    ]
                }
            ]
        },
        {
            "name": "Vernieuwingen",
            "topics": [
                {
                    "name": "",
                    "links": [
                        "Service verbeteren",
                        "Stationsvernieuwing"
                    ]
                }
            ]
        }

    ],
    "footer": {
        "text": "Een nachtje weg naar jouw favoriete stad?",
        "link": "Bekijk onze deals"
    }
},
{
    "name": "Producten",
    "headers": {}
},
{
    "name": "Dagje uit & Deals",
    "headers": {}
},
{
    "name": "Klantenservice",
    "headers": {}
}

]